src/__init__.py
src/conf/__init__.py
src/conf/config.yaml
src/search.py
src/subscraper.py
subsscraper-0.1.4.dist-info/METADATA
subsscraper-0.1.4.dist-info/WHEEL
subsscraper-0.1.4.dist-info/entry_points.txt
subsscraper-0.1.4.dist-info/RECORD
